{
    "entity_id": 1,
    "component_mask": 49713,
    "Body": {
        "value0": 0.0,
        "value1": {
            "value0": -5760.0,
            "value1": 940.0
        },
        "value2": {
            "value0": 0.0,
            "value1": 0.0
        },
        "value3": {
            "value0": 0.0,
            "value1": 1.0
        },
        "value4": {
            "value0": -1.0,
            "value1": 0.0
        },
        "value5": false
    },
    "Render": {
        "value0": {
            "value0": 230,
            "value1": 41,
            "value2": 55,
            "value3": 255
        }
    },
    "FumoRect": {
        "value0": -5760.0,
        "value1": 940.0,
        "value2": 20000.0,
        "value3": 200.0
    },
    "ColliderObjectFlag": {
        "value0": 0
    },
    "Screen": {
        "value0": 0,
        "value1": {
            "value0": 0.0,
            "value1": 0.0
        }
    },
    "LevelId": {
        "value0": 0
    },
    "entity_id": 2,
    "component_mask": 50321,
    "Body": {
        "value0": 0.0,
        "value1": {
            "value0": -5760.0,
            "value1": 740.0
        },
        "value2": {
            "value0": 0.0,
            "value1": 0.0
        },
        "value3": {
            "value0": 0.0,
            "value1": 1.0
        },
        "value4": {
            "value0": -1.0,
            "value1": 0.0
        },
        "value5": false
    },
    "Render": {
        "value0": {
            "value0": 255,
            "value1": 161,
            "value2": 0,
            "value3": 255
        }
    },
    "ParallelGravityField": {
        "value0": {
            "value0": -5760.0,
            "value1": 740.0,
            "value2": 20000.0,
            "value3": 200.0
        },
        "value1": {
            "value0": 0.0,
            "value1": 1.0
        },
        "value2": 900.0,
        "value3": 0.0
    },
    "GravFieldFlag": {
        "value0": 0
    },
    "Screen": {
        "value0": 0,
        "value1": {
            "value0": 0.0,
            "value1": 0.0
        }
    },
    "LevelId": {
        "value0": 0
    },
    "entity_id": 3,
    "component_mask": 49713,
    "Body": {
        "value0": 0.0,
        "value1": {
            "value0": 20000.0,
            "value1": 940.0
        },
        "value2": {
            "value0": 0.0,
            "value1": 0.0
        },
        "value3": {
            "value0": 0.0,
            "value1": 1.0
        },
        "value4": {
            "value0": -1.0,
            "value1": 0.0
        },
        "value5": false
    },
    "Render": {
        "value0": {
            "value0": 230,
            "value1": 41,
            "value2": 55,
            "value3": 255
        }
    },
    "FumoRect": {
        "value0": 20000.0,
        "value1": 940.0,
        "value2": 200.0,
        "value3": 200.0
    },
    "ColliderObjectFlag": {
        "value0": 0
    },
    "Screen": {
        "value0": 0,
        "value1": {
            "value0": 0.0,
            "value1": 0.0
        }
    },
    "LevelId": {
        "value0": 0
    },
    "entity_id": 4,
    "component_mask": 51761,
    "Body": {
        "value0": 0.0,
        "value1": {
            "value0": 20000.0,
            "value1": 940.0
        },
        "value2": {
            "value0": 0.0,
            "value1": 0.0
        },
        "value3": {
            "value0": 0.0,
            "value1": 1.0
        },
        "value4": {
            "value0": -1.0,
            "value1": 0.0
        },
        "value5": false
    },
    "Render": {
        "value0": {
            "value0": 230,
            "value1": 41,
            "value2": 55,
            "value3": 255
        }
    },
    "FumoRect": {
        "value0": 0.0,
        "value1": 0.0,
        "value2": 1920.0,
        "value3": 1080.0
    },
    "ColliderObjectFlag": {
        "value0": 0
    },
    "OutlineRectFlag": {
        "value0": 0
    },
    "Screen": {
        "value0": 0,
        "value1": {
            "value0": 0.0,
            "value1": 0.0
        }
    },
    "LevelId": {
        "value0": 0
    },
    "entity_id": 5,
    "component_mask": 51761,
    "Body": {
        "value0": 0.0,
        "value1": {
            "value0": 20000.0,
            "value1": 940.0
        },
        "value2": {
            "value0": 0.0,
            "value1": 0.0
        },
        "value3": {
            "value0": 0.0,
            "value1": 1.0
        },
        "value4": {
            "value0": -1.0,
            "value1": 0.0
        },
        "value5": false
    },
    "Render": {
        "value0": {
            "value0": 230,
            "value1": 41,
            "value2": 55,
            "value3": 255
        }
    },
    "FumoRect": {
        "value0": 1920.0,
        "value1": 0.0,
        "value2": 1920.0,
        "value3": 1080.0
    },
    "ColliderObjectFlag": {
        "value0": 0
    },
    "OutlineRectFlag": {
        "value0": 0
    },
    "Screen": {
        "value0": 0,
        "value1": {
            "value0": 0.0,
            "value1": 0.0
        }
    },
    "LevelId": {
        "value0": 0
    },
    "entity_id": 6,
    "component_mask": 51761,
    "Body": {
        "value0": 0.0,
        "value1": {
            "value0": 20000.0,
            "value1": 940.0
        },
        "value2": {
            "value0": 0.0,
            "value1": 0.0
        },
        "value3": {
            "value0": 0.0,
            "value1": 1.0
        },
        "value4": {
            "value0": -1.0,
            "value1": 0.0
        },
        "value5": false
    },
    "Render": {
        "value0": {
            "value0": 230,
            "value1": 41,
            "value2": 55,
            "value3": 255
        }
    },
    "FumoRect": {
        "value0": 3840.0,
        "value1": 0.0,
        "value2": 1920.0,
        "value3": 1080.0
    },
    "ColliderObjectFlag": {
        "value0": 0
    },
    "OutlineRectFlag": {
        "value0": 0
    },
    "Screen": {
        "value0": 0,
        "value1": {
            "value0": 0.0,
            "value1": 0.0
        }
    },
    "LevelId": {
        "value0": 0
    },
    "entity_id": 7,
    "component_mask": 51761,
    "Body": {
        "value0": 0.0,
        "value1": {
            "value0": 20000.0,
            "value1": 940.0
        },
        "value2": {
            "value0": 0.0,
            "value1": 0.0
        },
        "value3": {
            "value0": 0.0,
            "value1": 1.0
        },
        "value4": {
            "value0": -1.0,
            "value1": 0.0
        },
        "value5": false
    },
    "Render": {
        "value0": {
            "value0": 230,
            "value1": 41,
            "value2": 55,
            "value3": 255
        }
    },
    "FumoRect": {
        "value0": 5760.0,
        "value1": 0.0,
        "value2": 1920.0,
        "value3": 1080.0
    },
    "ColliderObjectFlag": {
        "value0": 0
    },
    "OutlineRectFlag": {
        "value0": 0
    },
    "Screen": {
        "value0": 0,
        "value1": {
            "value0": 0.0,
            "value1": 0.0
        }
    },
    "LevelId": {
        "value0": 0
    },
    "entity_id": 8,
    "component_mask": 49713,
    "Body": {
        "value0": 0.0,
        "value1": {
            "value0": -451.34619140625,
            "value1": 416.7998352050781
        },
        "value2": {
            "value0": 0.0,
            "value1": 0.0
        },
        "value3": {
            "value0": 0.0,
            "value1": 1.0
        },
        "value4": {
            "value0": -1.0,
            "value1": 0.0
        },
        "value5": false
    },
    "Render": {
        "value0": {
            "value0": 230,
            "value1": 41,
            "value2": 55,
            "value3": 255
        }
    },
    "FumoRect": {
        "value0": -320.0,
        "value1": 540.0,
        "value2": 200.0,
        "value3": 200.0
    },
    "ColliderObjectFlag": {
        "value0": 0
    },
    "Screen": {
        "value0": 0,
        "value1": {
            "value0": 0.0,
            "value1": 0.0
        }
    },
    "LevelId": {
        "value0": 0
    },
    "entity_id": 9,
    "component_mask": 50321,
    "Body": {
        "value0": 0.0,
        "value1": {
            "value0": -448.84619140625,
            "value1": 183.0498504638672
        },
        "value2": {
            "value0": 0.0,
            "value1": 0.0
        },
        "value3": {
            "value0": 0.0,
            "value1": 1.0
        },
        "value4": {
            "value0": -1.0,
            "value1": 0.0
        },
        "value5": false
    },
    "Render": {
        "value0": {
            "value0": 255,
            "value1": 161,
            "value2": 0,
            "value3": 255
        }
    },
    "ParallelGravityField": {
        "value0": {
            "value0": -448.84619140625,
            "value1": 183.0498504638672,
            "value2": 200.0,
            "value3": 200.0
        },
        "value1": {
            "value0": 0.0,
            "value1": 1.0
        },
        "value2": 900.0,
        "value3": 0.0
    },
    "GravFieldFlag": {
        "value0": 0
    },
    "Screen": {
        "value0": 0,
        "value1": {
            "value0": 0.0,
            "value1": 0.0
        }
    },
    "LevelId": {
        "value0": 0
    },
    "entity_id": 10,
    "component_mask": 49713,
    "Body": {
        "value0": 0.0,
        "value1": {
            "value0": -960.0,
            "value1": 540.0
        },
        "value2": {
            "value0": 0.0,
            "value1": 0.0
        },
        "value3": {
            "value0": 0.0,
            "value1": 1.0
        },
        "value4": {
            "value0": -1.0,
            "value1": 0.0
        },
        "value5": false
    },
    "Render": {
        "value0": {
            "value0": 230,
            "value1": 41,
            "value2": 55,
            "value3": 255
        }
    },
    "FumoRect": {
        "value0": -960.0,
        "value1": 540.0,
        "value2": 200.0,
        "value3": 200.0
    },
    "ColliderObjectFlag": {
        "value0": 0
    },
    "Screen": {
        "value0": 0,
        "value1": {
            "value0": 0.0,
            "value1": 0.0
        }
    },
    "LevelId": {
        "value0": 0
    },
    "entity_id": 11,
    "component_mask": 50321,
    "Body": {
        "value0": 0.0,
        "value1": {
            "value0": -960.0,
            "value1": 340.0
        },
        "value2": {
            "value0": 0.0,
            "value1": 0.0
        },
        "value3": {
            "value0": 0.0,
            "value1": 1.0
        },
        "value4": {
            "value0": -1.0,
            "value1": 0.0
        },
        "value5": false
    },
    "Render": {
        "value0": {
            "value0": 255,
            "value1": 161,
            "value2": 0,
            "value3": 255
        }
    },
    "ParallelGravityField": {
        "value0": {
            "value0": -960.0,
            "value1": 340.0,
            "value2": 200.0,
            "value3": 200.0
        },
        "value1": {
            "value0": 0.0,
            "value1": 1.0
        },
        "value2": 900.0,
        "value3": 0.0
    },
    "GravFieldFlag": {
        "value0": 0
    },
    "Screen": {
        "value0": 0,
        "value1": {
            "value0": 0.0,
            "value1": 0.0
        }
    },
    "LevelId": {
        "value0": 0
    },
    "entity_id": 12,
    "component_mask": 49713,
    "Body": {
        "value0": 0.0,
        "value1": {
            "value0": -1600.0,
            "value1": 540.0
        },
        "value2": {
            "value0": 0.0,
            "value1": 0.0
        },
        "value3": {
            "value0": 0.0,
            "value1": 1.0
        },
        "value4": {
            "value0": -1.0,
            "value1": 0.0
        },
        "value5": false
    },
    "Render": {
        "value0": {
            "value0": 230,
            "value1": 41,
            "value2": 55,
            "value3": 255
        }
    },
    "FumoRect": {
        "value0": -1600.0,
        "value1": 540.0,
        "value2": 200.0,
        "value3": 200.0
    },
    "ColliderObjectFlag": {
        "value0": 0
    },
    "Screen": {
        "value0": 0,
        "value1": {
            "value0": 0.0,
            "value1": 0.0
        }
    },
    "LevelId": {
        "value0": 0
    },
    "entity_id": 13,
    "component_mask": 50321,
    "Body": {
        "value0": 0.0,
        "value1": {
            "value0": -1600.0,
            "value1": 340.0
        },
        "value2": {
            "value0": 0.0,
            "value1": 0.0
        },
        "value3": {
            "value0": 0.0,
            "value1": 1.0
        },
        "value4": {
            "value0": -1.0,
            "value1": 0.0
        },
        "value5": false
    },
    "Render": {
        "value0": {
            "value0": 255,
            "value1": 161,
            "value2": 0,
            "value3": 255
        }
    },
    "ParallelGravityField": {
        "value0": {
            "value0": -1600.0,
            "value1": 340.0,
            "value2": 200.0,
            "value3": 200.0
        },
        "value1": {
            "value0": 0.0,
            "value1": 1.0
        },
        "value2": 900.0,
        "value3": 0.0
    },
    "GravFieldFlag": {
        "value0": 0
    },
    "Screen": {
        "value0": 0,
        "value1": {
            "value0": 0.0,
            "value1": 0.0
        }
    },
    "LevelId": {
        "value0": 0
    },
    "entity_id": 14,
    "component_mask": 49713,
    "Body": {
        "value0": 0.0,
        "value1": {
            "value0": -2240.0,
            "value1": 540.0
        },
        "value2": {
            "value0": 0.0,
            "value1": 0.0
        },
        "value3": {
            "value0": 0.0,
            "value1": 1.0
        },
        "value4": {
            "value0": -1.0,
            "value1": 0.0
        },
        "value5": false
    },
    "Render": {
        "value0": {
            "value0": 230,
            "value1": 41,
            "value2": 55,
            "value3": 255
        }
    },
    "FumoRect": {
        "value0": -2240.0,
        "value1": 540.0,
        "value2": 200.0,
        "value3": 200.0
    },
    "ColliderObjectFlag": {
        "value0": 0
    },
    "Screen": {
        "value0": 0,
        "value1": {
            "value0": 0.0,
            "value1": 0.0
        }
    },
    "LevelId": {
        "value0": 0
    },
    "entity_id": 15,
    "component_mask": 50321,
    "Body": {
        "value0": 0.0,
        "value1": {
            "value0": -2240.0,
            "value1": 340.0
        },
        "value2": {
            "value0": 0.0,
            "value1": 0.0
        },
        "value3": {
            "value0": 0.0,
            "value1": 1.0
        },
        "value4": {
            "value0": -1.0,
            "value1": 0.0
        },
        "value5": false
    },
    "Render": {
        "value0": {
            "value0": 255,
            "value1": 161,
            "value2": 0,
            "value3": 255
        }
    },
    "ParallelGravityField": {
        "value0": {
            "value0": -2240.0,
            "value1": 340.0,
            "value2": 200.0,
            "value3": 200.0
        },
        "value1": {
            "value0": 0.0,
            "value1": 1.0
        },
        "value2": 900.0,
        "value3": 0.0
    },
    "GravFieldFlag": {
        "value0": 0
    },
    "Screen": {
        "value0": 0,
        "value1": {
            "value0": 0.0,
            "value1": 0.0
        }
    },
    "LevelId": {
        "value0": 0
    },
    "entity_id": 16,
    "component_mask": 49713,
    "Body": {
        "value0": 0.0,
        "value1": {
            "value0": -2880.0,
            "value1": 540.0
        },
        "value2": {
            "value0": 0.0,
            "value1": 0.0
        },
        "value3": {
            "value0": 0.0,
            "value1": 1.0
        },
        "value4": {
            "value0": -1.0,
            "value1": 0.0
        },
        "value5": false
    },
    "Render": {
        "value0": {
            "value0": 230,
            "value1": 41,
            "value2": 55,
            "value3": 255
        }
    },
    "FumoRect": {
        "value0": -2880.0,
        "value1": 540.0,
        "value2": 200.0,
        "value3": 200.0
    },
    "ColliderObjectFlag": {
        "value0": 0
    },
    "Screen": {
        "value0": 0,
        "value1": {
            "value0": 0.0,
            "value1": 0.0
        }
    },
    "LevelId": {
        "value0": 0
    },
    "entity_id": 17,
    "component_mask": 50321,
    "Body": {
        "value0": 0.0,
        "value1": {
            "value0": -2880.0,
            "value1": 340.0
        },
        "value2": {
            "value0": 0.0,
            "value1": 0.0
        },
        "value3": {
            "value0": 0.0,
            "value1": 1.0
        },
        "value4": {
            "value0": -1.0,
            "value1": 0.0
        },
        "value5": false
    },
    "Render": {
        "value0": {
            "value0": 255,
            "value1": 161,
            "value2": 0,
            "value3": 255
        }
    },
    "ParallelGravityField": {
        "value0": {
            "value0": -2880.0,
            "value1": 340.0,
            "value2": 200.0,
            "value3": 200.0
        },
        "value1": {
            "value0": 0.0,
            "value1": 1.0
        },
        "value2": 900.0,
        "value3": 0.0
    },
    "GravFieldFlag": {
        "value0": 0
    },
    "Screen": {
        "value0": 0,
        "value1": {
            "value0": 0.0,
            "value1": 0.0
        }
    },
    "LevelId": {
        "value0": 0
    },
    "entity_id": 18,
    "component_mask": 49713,
    "Body": {
        "value0": 0.0,
        "value1": {
            "value0": -3520.0,
            "value1": 540.0
        },
        "value2": {
            "value0": 0.0,
            "value1": 0.0
        },
        "value3": {
            "value0": 0.0,
            "value1": 1.0
        },
        "value4": {
            "value0": -1.0,
            "value1": 0.0
        },
        "value5": false
    },
    "Render": {
        "value0": {
            "value0": 230,
            "value1": 41,
            "value2": 55,
            "value3": 255
        }
    },
    "FumoRect": {
        "value0": -3520.0,
        "value1": 540.0,
        "value2": 200.0,
        "value3": 200.0
    },
    "ColliderObjectFlag": {
        "value0": 0
    },
    "Screen": {
        "value0": 0,
        "value1": {
            "value0": 0.0,
            "value1": 0.0
        }
    },
    "LevelId": {
        "value0": 0
    },
    "entity_id": 19,
    "component_mask": 50321,
    "Body": {
        "value0": 0.0,
        "value1": {
            "value0": -3520.0,
            "value1": 340.0
        },
        "value2": {
            "value0": 0.0,
            "value1": 0.0
        },
        "value3": {
            "value0": 0.0,
            "value1": 1.0
        },
        "value4": {
            "value0": -1.0,
            "value1": 0.0
        },
        "value5": false
    },
    "Render": {
        "value0": {
            "value0": 255,
            "value1": 161,
            "value2": 0,
            "value3": 255
        }
    },
    "ParallelGravityField": {
        "value0": {
            "value0": -3520.0,
            "value1": 340.0,
            "value2": 200.0,
            "value3": 200.0
        },
        "value1": {
            "value0": 0.0,
            "value1": 1.0
        },
        "value2": 900.0,
        "value3": 0.0
    },
    "GravFieldFlag": {
        "value0": 0
    },
    "Screen": {
        "value0": 0,
        "value1": {
            "value0": 0.0,
            "value1": 0.0
        }
    },
    "LevelId": {
        "value0": 0
    },
    "entity_id": 20,
    "component_mask": 51761,
    "Body": {
        "value0": 0.0,
        "value1": {
            "value0": 20000.0,
            "value1": 940.0
        },
        "value2": {
            "value0": 0.0,
            "value1": 0.0
        },
        "value3": {
            "value0": 0.0,
            "value1": 1.0
        },
        "value4": {
            "value0": -1.0,
            "value1": 0.0
        },
        "value5": false
    },
    "Render": {
        "value0": {
            "value0": 230,
            "value1": 41,
            "value2": 55,
            "value3": 255
        }
    },
    "FumoRect": {
        "value0": 0.0,
        "value1": 0.0,
        "value2": 1920.0,
        "value3": 1080.0
    },
    "ColliderObjectFlag": {
        "value0": 0
    },
    "OutlineRectFlag": {
        "value0": 0
    },
    "Screen": {
        "value0": 0,
        "value1": {
            "value0": 0.0,
            "value1": 0.0
        }
    },
    "LevelId": {
        "value0": 0
    },
    "entity_id": 21,
    "component_mask": 49713,
    "Body": {
        "value0": 0.0,
        "value1": {
            "value0": -86.29864501953125,
            "value1": 747.9998779296875
        },
        "value2": {
            "value0": 0.0,
            "value1": 0.0
        },
        "value3": {
            "value0": 0.0,
            "value1": 1.0
        },
        "value4": {
            "value0": -1.0,
            "value1": 0.0
        },
        "value5": false
    },
    "Render": {
        "value0": {
            "value0": 230,
            "value1": 41,
            "value2": 55,
            "value3": 255
        }
    },
    "FumoRect": {
        "value0": -161.25001525878907,
        "value1": 681.790283203125,
        "value2": 200.0,
        "value3": 200.0
    },
    "ColliderObjectFlag": {
        "value0": 0
    },
    "Screen": {
        "value0": 0,
        "value1": {
            "value0": 0.0,
            "value1": 0.0
        }
    },
    "LevelId": {
        "value0": 0
    },
    "entity_id": 22,
    "component_mask": 49713,
    "Body": {
        "value0": 0.0,
        "value1": {
            "value0": -773.5726318359375,
            "value1": -35.705902099609378
        },
        "value2": {
            "value0": 0.0,
            "value1": 0.0
        },
        "value3": {
            "value0": 0.0,
            "value1": 1.0
        },
        "value4": {
            "value0": -1.0,
            "value1": 0.0
        },
        "value5": false
    },
    "Render": {
        "value0": {
            "value0": 230,
            "value1": 41,
            "value2": 55,
            "value3": 255
        }
    },
    "FumoRect": {
        "value0": -597.0341186523438,
        "value1": 17.274917602539064,
        "value2": 200.0,
        "value3": 200.0
    },
    "ColliderObjectFlag": {
        "value0": 0
    },
    "Screen": {
        "value0": 0,
        "value1": {
            "value0": 0.0,
            "value1": 0.0
        }
    },
    "LevelId": {
        "value0": 0
    },
    "entity_id": 23,
    "component_mask": 49713,
    "Body": {
        "value0": 0.0,
        "value1": {
            "value0": 863.4302368164063,
            "value1": -2.81817626953125
        },
        "value2": {
            "value0": 0.0,
            "value1": 0.0
        },
        "value3": {
            "value0": 0.0,
            "value1": 1.0
        },
        "value4": {
            "value0": -1.0,
            "value1": 0.0
        },
        "value5": false
    },
    "Render": {
        "value0": {
            "value0": 230,
            "value1": 41,
            "value2": 55,
            "value3": 255
        }
    },
    "FumoRect": {
        "value0": 334.1484375,
        "value1": 188.74246215820313,
        "value2": 200.0,
        "value3": 200.0
    },
    "ColliderObjectFlag": {
        "value0": 0
    },
    "Screen": {
        "value0": 0,
        "value1": {
            "value0": 0.0,
            "value1": 0.0
        }
    },
    "LevelId": {
        "value0": 0
    },
    "entity_id": 24,
    "component_mask": 49713,
    "Body": {
        "value0": 0.0,
        "value1": {
            "value0": 829.7062377929688,
            "value1": 254.1737060546875
        },
        "value2": {
            "value0": 0.0,
            "value1": 0.0
        },
        "value3": {
            "value0": 0.0,
            "value1": 1.0
        },
        "value4": {
            "value0": -1.0,
            "value1": 0.0
        },
        "value5": false
    },
    "Render": {
        "value0": {
            "value0": 230,
            "value1": 41,
            "value2": 55,
            "value3": 255
        }
    },
    "FumoRect": {
        "value0": 512.4998779296875,
        "value1": 292.8075866699219,
        "value2": 200.0,
        "value3": 200.0
    },
    "ColliderObjectFlag": {
        "value0": 0
    },
    "Screen": {
        "value0": 0,
        "value1": {
            "value0": 0.0,
            "value1": 0.0
        }
    },
    "LevelId": {
        "value0": 0
    },
    "entity_id": 25,
    "component_mask": 49713,
    "Body": {
        "value0": 0.0,
        "value1": {
            "value0": 600.3545532226563,
            "value1": 505.8281555175781
        },
        "value2": {
            "value0": 0.0,
            "value1": 0.0
        },
        "value3": {
            "value0": 0.0,
            "value1": 1.0
        },
        "value4": {
            "value0": -1.0,
            "value1": 0.0
        },
        "value5": false
    },
    "Render": {
        "value0": {
            "value0": 230,
            "value1": 41,
            "value2": 55,
            "value3": 255
        }
    },
    "FumoRect": {
        "value0": 757.5010986328125,
        "value1": 495.365234375,
        "value2": 200.0,
        "value3": 200.0
    },
    "ColliderObjectFlag": {
        "value0": 0
    },
    "Screen": {
        "value0": 0,
        "value1": {
            "value0": 0.0,
            "value1": 0.0
        }
    },
    "LevelId": {
        "value0": 0
    },
    "entity_id": 26,
    "component_mask": 50321,
    "Body": {
        "value0": 0.0,
        "value1": {
            "value0": 802.0211791992188,
            "value1": 500.8281555175781
        },
        "value2": {
            "value0": 0.0,
            "value1": 0.0
        },
        "value3": {
            "value0": 0.0,
            "value1": 1.0
        },
        "value4": {
            "value0": -1.0,
            "value1": 0.0
        },
        "value5": false
    },
    "Render": {
        "value0": {
            "value0": 255,
            "value1": 161,
            "value2": 0,
            "value3": 255
        }
    },
    "ParallelGravityField": {
        "value0": {
            "value0": 802.0211791992188,
            "value1": 500.8281555175781,
            "value2": 200.0,
            "value3": 200.0
        },
        "value1": {
            "value0": 0.0,
            "value1": 1.0
        },
        "value2": 900.0,
        "value3": 0.0
    },
    "GravFieldFlag": {
        "value0": 0
    },
    "Screen": {
        "value0": 0,
        "value1": {
            "value0": 0.0,
            "value1": 0.0
        }
    },
    "LevelId": {
        "value0": 0
    },
    "entity_id": 46,
    "component_mask": 49713,
    "Body": {
        "value0": 0.0,
        "value1": {
            "value0": 1367.067626953125,
            "value1": 541.1961669921875
        },
        "value2": {
            "value0": 0.0,
            "value1": 0.0
        },
        "value3": {
            "value0": 0.0,
            "value1": 1.0
        },
        "value4": {
            "value0": -1.0,
            "value1": 0.0
        },
        "value5": false
    },
    "Render": {
        "value0": {
            "value0": 230,
            "value1": 41,
            "value2": 55,
            "value3": 255
        }
    },
    "FumoRect": {
        "value0": 1136.9085693359376,
        "value1": 260.353271484375,
        "value2": 200.0,
        "value3": 200.0
    },
    "ColliderObjectFlag": {
        "value0": 0
    },
    "Screen": {
        "value0": 0,
        "value1": {
            "value0": 0.0,
            "value1": 0.0
        }
    },
    "LevelId": {
        "value0": 0
    }
}